MANIFEST.in
README.md
setup.py
mimiron/__init__.py
mimiron/command_line.py
mimiron.egg-info/PKG-INFO
mimiron.egg-info/SOURCES.txt
mimiron.egg-info/dependency_links.txt
mimiron.egg-info/entry_points.txt
mimiron.egg-info/requires.txt
mimiron.egg-info/top_level.txt
mimiron/core/__init__.py
mimiron/core/config.py
mimiron/core/constants.py
mimiron/core/io.py
mimiron/core/commands/__init__.py
mimiron/core/commands/bump.py
mimiron/core/commands/deploy.py
mimiron/core/commands/status.py
mimiron/core/util/__init__.py
mimiron/core/util/time.py
mimiron/exceptions/__init__.py
mimiron/exceptions/commands.py
mimiron/exceptions/config.py
mimiron/exceptions/vendor.py
mimiron/schemas/__init__.py
mimiron/schemas/config.py
mimiron/vendor/__init__.py
mimiron/vendor/dockerhub.py
mimiron/vendor/terraform.py
mimiron/vendor/git_extensions/__init__.py
mimiron/vendor/git_extensions/extensions.py
mimiron/vendor/git_extensions/helpers.py
mimiron/vendor/git_extensions/parsers.py
mimiron/vendor/git_extensions/util.py