Metadata-Version: 1.1
Name: mimiron
Version: 0.4.2
Summary: Mimiron is a CLI tool whose purpose is to provide a better workflow when manging tfvars
Home-page: https://github.com/ImageIntelligence/mimiron
Author: David Vuong
Author-email: david@imageintelligence.com
License: UNKNOWN
Platform: UNKNOWN
Classifier: Intended Audience :: Developers
Classifier: Environment :: Console
Classifier: Topic :: Utilities
Classifier: Programming Language :: Python :: 2 :: Only
Classifier: Programming Language :: Python :: 2.6
Classifier: Programming Language :: Python :: 2.7
